[
  {
    "trackingCode": "PKG001",
    "status": "In Transit",
    "location": "Distribution Center - New York",
    "receiverName": "John Doe",
    "receiverEmail": "john.doe@email.com",
    "receiverPhone": "+1 (555) 123-4567",
    "deliveryAddress": "123 Main Street, Apt 4B, New York, NY 10001",
    "senderName": "Jane Smith",
    "senderEmail": "jane.smith@company.com",
    "senderAddress": "456 Business Ave, Los Angeles, CA 90001",
    "createdAt": "2026-01-06T10:30:00.000Z",
    "lastUpdated": "2026-01-08T10:30:00.000Z"
  },
  {
    "trackingCode": "PKG002",
    "status": "Out for Delivery",
    "location": "Local Hub - Brooklyn",
    "receiverName": "Jane Smith",
    "receiverEmail": "jane.smith@email.com",
    "receiverPhone": "+1 (555) 987-6543",
    "deliveryAddress": "456 Oak Avenue, Brooklyn, NY 11201",
    "senderName": "Mike Johnson",
    "senderEmail": "mike.j@store.com",
    "senderAddress": "789 Warehouse Road, Chicago, IL 60601",
    "createdAt": "2026-01-07T09:15:00.000Z",
    "lastUpdated": "2026-01-08T09:15:00.000Z"
  },
  {
    "trackingCode": "66FA12",
    "status": "On-Hold",
    "location": "Toronto, Canada",
    "receiverName": "Katiana Guillaume",
    "receiverEmail": "gkatiana13@gmail.com",
    "receiverPhone": "+1 645-200-2262",
    "deliveryAddress": "20440 NW 17th ave, Miami Gardens, Fl 33056",
    "createdAt": "2026-01-13T09:21:06.797Z",
    "lastUpdated": "2026-01-17T22:24:16.420Z",
    "senderName": "Maison Birks",
    "senderEmail": "edwardjonathan@maisonbirks.com",
    "senderAddress": "162 Cumberland Street, Toronto, ON M5R 3N5 CN"
  }
]